dotfilebackup/__init__.py
dotfilebackup/dotfilebackup.py
dotfilebackup-0.0.1.dist-info/METADATA
dotfilebackup-0.0.1.dist-info/WHEEL
dotfilebackup-0.0.1.dist-info/licenses/LICENSE
dotfilebackup-0.0.1.dist-info/RECORD
