Metadata-Version: 2.1
Name: dotfilebackup
Version: 0.0.1
Summary: cli app for creating backups using .backup yaml configuration files
Project-URL: Homepage, https://notabug.org/fil/dotfilebackup
Author-email: Filip Dobrowolski <447823.dotfilebackup.p.f@dob.nz>
License-File: LICENSE
Classifier: Development Status :: 1 - Planning
Classifier: Operating System :: OS Independent
Classifier: Programming Language :: Python :: 3
Requires-Python: >=3.11
